AUTHORS.md
LICENSE.md
MANIFEST.in
README.md
pyproject.toml
requirements.txt
setup.py
cython/tetrahedron2.pyx
pycoordinates/__init__.py
pycoordinates/attrs.py
pycoordinates/basis.py
pycoordinates/cell.py
pycoordinates/grid.py
pycoordinates/test_basis.py
pycoordinates/test_cell.py
pycoordinates/test_grid.py
pycoordinates/test_tetrahedron.py
pycoordinates/test_util.py
pycoordinates/triangulation.py
pycoordinates/util.py
pycoordinates.egg-info/PKG-INFO
pycoordinates.egg-info/SOURCES.txt
pycoordinates.egg-info/dependency_links.txt
pycoordinates.egg-info/requires.txt
pycoordinates.egg-info/top_level.txt