Metadata-Version: 2.1
Name: pycoordinates
Version: 0.1.1
Summary: Create and manipulate coordinates in vector bases
Author: pycoordinates contributors
Author-email: gpulkin@gmail.com
License: UNKNOWN
Platform: UNKNOWN
License-File: LICENSE.md
License-File: AUTHORS.md
